LICENSE
README.md
setup.py
VisualQ/__init__.py
VisualQ.egg-info/PKG-INFO
VisualQ.egg-info/SOURCES.txt
VisualQ.egg-info/dependency_links.txt
VisualQ.egg-info/requires.txt
VisualQ.egg-info/top_level.txt
VisualQ/deepquantum/__init__.py
VisualQ/deepquantum/circuit.py
VisualQ/deepquantum/gates.py
VisualQ/deepquantum/utils.py
VisualQ/deepquantum/nn/__init__.py
VisualQ/deepquantum/nn/dequconv.py
VisualQ/deepquantum/nn/dequpool.py
VisualQ/deepquantum/nn/quattention.py
VisualQ/deepquantum/nn/quconv.py
VisualQ/deepquantum/nn/quconvAE.py
VisualQ/deepquantum/nn/qugat.py
VisualQ/deepquantum/nn/qugru.py
VisualQ/deepquantum/nn/qulinear.py
VisualQ/deepquantum/nn/quml.py
VisualQ/deepquantum/nn/qupool.py
VisualQ/deepquantum/nn/qureinforce.py
VisualQ/deepquantum/nn/qusaae.py
VisualQ/deepquantum/test/__init__.py
VisualQ/deepquantum/test/simple_conv.py